fillbib.py
filltex-1.7.4.data/scripts/fillbib
filltex-1.7.4.data/scripts/filltex
filltex-1.7.4.dist-info/licenses/LICENSE
filltex-1.7.4.dist-info/METADATA
filltex-1.7.4.dist-info/WHEEL
filltex-1.7.4.dist-info/top_level.txt
filltex-1.7.4.dist-info/RECORD
