Metadata-Version: 2.4
Name: filltex
Version: 1.7.4
Summary: Automatic queries to ADS and InSPIRE databases to fill LATEX bibliography
Home-page: https://github.com/dgerosa/filltex
Author: Davide Gerosa and Michele Vallisneri
Author-email: davide.gerosa@unimib.it
License: MIT
License-File: LICENSE
Dynamic: author
Dynamic: author-email
Dynamic: description
Dynamic: home-page
Dynamic: license
Dynamic: license-file
Dynamic: summary
